caffeine/__init__.py
caffeine/__main__.py
caffeine/cli.py
caffeine/config.py
caffeine/github.py
caffeine/models.py
caffeine/ui/__init__.py
caffeine/ui/components.py
caffeine/ui/dashboard.py
caffeine/ui/themes.py
caffeine_gitvs-0.1.0.dist-info/METADATA
caffeine_gitvs-0.1.0.dist-info/WHEEL
caffeine_gitvs-0.1.0.dist-info/entry_points.txt
caffeine_gitvs-0.1.0.dist-info/licenses/LICENSE
caffeine_gitvs-0.1.0.dist-info/RECORD
