Metadata-Version: 2.4
Name: caffeine-gitvs
Version: 0.1.0
Summary: GitHub repo visualizer for terminal
Project-URL: Homepage, https://github.com/shafayet98/caffeine-gitvs
Project-URL: Repository, https://github.com/shafayet98/caffeine-gitvs
Author-email: "Shafayet Ul Islam (Audrie)" <shafayet.islam.61@gmail.com>
License: MIT
License-File: LICENSE
Keywords: cli,github,rich,terminal,visualization
Classifier: Development Status :: 3 - Alpha
Classifier: Environment :: Console
Classifier: Intended Audience :: Developers
Classifier: License :: OSI Approved :: MIT License
Classifier: Programming Language :: Python :: 3
Classifier: Programming Language :: Python :: 3.9
Classifier: Programming Language :: Python :: 3.10
Classifier: Programming Language :: Python :: 3.11
Classifier: Programming Language :: Python :: 3.12
Classifier: Topic :: Software Development :: Version Control :: Git
Requires-Python: >=3.9
Requires-Dist: httpx>=0.25.0
Requires-Dist: rich>=13.0.0
Requires-Dist: typer>=0.9.0
Provides-Extra: dev
Requires-Dist: pytest-cov>=4.0.0; extra == 'dev'
Requires-Dist: pytest>=7.0.0; extra == 'dev'
